pypdn/__init__.py
pypdn/_version.py
pypdn/namedlist.py
pypdn/nrbf.py
pypdn/reader.py
pypdn/util.py
tests/__init__.py
tests/test_namedlist.py
tests/test_nrbf.py
tests/test_reader.py
tests/util.py
tests/data/FlattenAdditiveTest.png
tests/data/FlattenBlendTest.pdn
tests/data/FlattenColorBurnTest.png
tests/data/FlattenColorDodgeTest.png
tests/data/FlattenDarkenTest.png
tests/data/FlattenDifferenceTest.png
tests/data/FlattenGlowTest.png
tests/data/FlattenLightenTest.png
tests/data/FlattenNegationTest.png
tests/data/FlattenOverlayTest.png
tests/data/FlattenReflectTest.png
tests/data/FlattenScreenTest.png
tests/data/FlattenXORTest.png
tests/data/Untitled.pdn
tests/data/Untitled2.pdn
tests/data/Untitled3.pdn
tests/data/arraysSerialized
tests/data/flattenMultiplyTest.png
tests/data/flattenNormalTest.png
tests/data/flattenNormalTest2.png
tests/data/flattenOpacityTest.png
tests/data/imageRawNRBF
tests/data/layerVisibleTest1.png
tests/data/layerVisibleTest2.png
tests/data/layerVisibleTest3.png
tests/data/oldPDN3510.pdn
tests/data/oldPDN3510.png
pypdn-1.0.6.dist-info/LICENSE
pypdn-1.0.6.dist-info/METADATA
pypdn-1.0.6.dist-info/WHEEL
pypdn-1.0.6.dist-info/top_level.txt
pypdn-1.0.6.dist-info/RECORD
