Metadata-Version: 2.1
Name: pypdn
Version: 1.0.6
Summary: Python package to read and write Paint.NET (PDN) images.
Home-page: https://github.com/addisonElliott/pypdn
Author: Addison Elliott
Author-email: addison.elliott@gmail.com
License: MIT License
Project-URL: Documentation, https://github.com/addisonElliott/pypdn
Project-URL: Source, https://github.com/addisonElliott/pypdn
Project-URL: Tracker, https://github.com/addisonElliott/pypdn/issues
Keywords: paint dot net paintdotnet dotnet .net pdn library read write save layered images image editor
Platform: UNKNOWN
Classifier: Development Status :: 4 - Beta
Classifier: Topic :: Scientific/Engineering
Classifier: License :: OSI Approved :: MIT License
Classifier: Programming Language :: Python
Classifier: Programming Language :: Python :: 3
Classifier: Programming Language :: Python :: 3.4
Classifier: Programming Language :: Python :: 3.5
Classifier: Programming Language :: Python :: 3.6
Classifier: Programming Language :: Python :: 3.7
Classifier: Programming Language :: Python :: 3.8
Classifier: Operating System :: OS Independent
Requires-Python: >=3.4
Requires-Dist: numpy (>=1.12)
Requires-Dist: aenum (>=1.0)
